mechanical_model/__init__.py
mechanical_model/diagram.py
mechanical_model/linear_mech.py
mechanical_model-0.0.1.dist-info/METADATA
mechanical_model-0.0.1.dist-info/WHEEL
mechanical_model-0.0.1.dist-info/licenses/LICENSE
mechanical_model-0.0.1.dist-info/RECORD
