Metadata-Version: 2.4
Name: mechanical_model
Version: 0.0.1
Summary: A package to deal with mechanical models and their linear response in oscillations, creep, microrheology, etc.
Project-URL: Homepage, https://github.com/MathieuLeocmach/mechanical_model
Project-URL: Issues, https://github.com/MathieuLeocmach/mechanical_model/issues
Author-email: Mathieu Leocmach <mathieu.leocmachr@univ-lyon1.fr>
License-Expression: GPL-3.0-or-later
License-File: LICENSE
Classifier: Operating System :: OS Independent
Classifier: Programming Language :: Python :: 3
Requires-Python: >=3.9
